MANIFEST.in
README.txt
TODO.txt
golismero.conf
golismero.py
requirements.txt
requirements_unix.txt
setup.py
data/cacert.pem
golismero/.DS_Store
golismero/__init__.py
golismero/__init__.pyc
golismero/common.py
golismero/common.pyc
golismero.egg-info/PKG-INFO
golismero.egg-info/SOURCES.txt
golismero.egg-info/dependency_links.txt
golismero.egg-info/requires.txt
golismero.egg-info/top_level.txt
golismero/api/.DS_Store
golismero/api/__init__.py
golismero/api/__init__.pyc
golismero/api/audit.py
golismero/api/audit.pyc
golismero/api/config.py
golismero/api/config.pyc
golismero/api/crypto.py
golismero/api/crypto.pyc
golismero/api/external.py
golismero/api/external.pyc
golismero/api/localfile.py
golismero/api/localfile.pyc
golismero/api/logger.py
golismero/api/logger.pyc
golismero/api/parallel.py
golismero/api/parallel.pyc
golismero/api/plugin.py
golismero/api/plugin.pyc
golismero/api/progress.py
golismero/api/progress.pyc
golismero/api/shared.py
golismero/api/shared.pyc
golismero/api/data/__init__.py
golismero/api/data/__init__.pyc
golismero/api/data/db.py
golismero/api/data/db.pyc
golismero/api/data/information/__init__.py
golismero/api/data/information/__init__.pyc
golismero/api/data/information/asn.py
golismero/api/data/information/asn.pyc
golismero/api/data/information/auth.py
golismero/api/data/information/auth.pyc
golismero/api/data/information/banner.py
golismero/api/data/information/banner.pyc
golismero/api/data/information/binary.py
golismero/api/data/information/binary.pyc
golismero/api/data/information/dns.py
golismero/api/data/information/dns.pyc
golismero/api/data/information/fingerprint.py
golismero/api/data/information/fingerprint.pyc
golismero/api/data/information/geolocation.py
golismero/api/data/information/geolocation.pyc
golismero/api/data/information/html.py
golismero/api/data/information/html.pyc
golismero/api/data/information/http.py
golismero/api/data/information/http.pyc
golismero/api/data/information/image.py
golismero/api/data/information/portscan.py
golismero/api/data/information/portscan.pyc
golismero/api/data/information/text.py
golismero/api/data/information/text.pyc
