Metadata-Version: 1.1
Name: golismero
Version: 2.0.3
Summary: GoLismero: The web knife. GoLismero is an open source framework for security testing.It's currently     geared towards web security, but it can easily be expanded to other kinds of scans.
Home-page: https://github.com/golismero
Author: GoLismero team
Author-email: golismero.project@gmail.com
License: GPL2
Download-URL: https://github.com/golismero/golismero/archive/master.zip
Platform: UNKNOWN
Classifier: Topic :: Security
Classifier: Environment :: Console
Classifier: Development Status :: 4 - Beta
Classifier: Operating System :: OS Independent
Classifier: Programming Language :: Python :: 2.7
Classifier: Intended Audience :: Information Technology
Classifier: License :: OSI Approved :: GNU General Public License v2 (GPLv2)
